{"id":"M66BMWMQJX1E9","name":"acc21625627400cf7583cd9b01685c74","size":115193,"btime":1737454646016,"mtime":1737454646474,"ext":"jpg","tags":[],"folders":["M7WYQX18Z8VR5"],"isDeleted":false,"url":"","annotation":"","modificationTime":1741246348392,"height":1200,"width":800,"lastModified":1741246818585,"palettes":[{"color":[48,39,75],"ratio":46},{"color":[85,87,145],"ratio":13},{"color":[15,12,20],"ratio":11},{"color":[204,117,178],"ratio":7},{"color":[90,45,84],"ratio":7},{"color":[102,122,183],"ratio":6},{"color":[122,56,94],"ratio":5},{"color":[128,167,216],"ratio":0.92},{"color":[230,217,242],"ratio":0.63}]}