{"id":"M91OY527MRDZV","name":"4592a8f85e1d3120519defd2b328a87c","size":507032,"btime":1743705022103,"mtime":1743705022132,"ext":"jpg","tags":[],"folders":[],"isDeleted":false,"url":"","annotation":"","modificationTime":1743705022133,"height":2048,"width":1305,"lastModified":1743705022295,"palettes":[{"color":[76,85,95],"ratio":51},{"color":[20,23,23],"ratio":16},{"color":[206,208,205],"ratio":14},{"color":[143,148,149],"ratio":8},{"color":[120,134,142],"ratio":3.27},{"color":[118,148,185],"ratio":2.85},{"color":[159,178,195],"ratio":2.31},{"color":[111,122,144],"ratio":0.85}]}