{"id":"M8M04Y3MIHO2D","name":"dgxydqc-cca2789d-2605-449a-b813-081f9f1e36e2","size":345253,"btime":1710767872832,"mtime":1710767874445,"ext":"jpg","tags":[],"folders":["M7X33YC146JSB"],"isDeleted":false,"url":"","annotation":"","modificationTime":1742756355490,"height":2048,"width":1448,"lastModified":1742756355621,"palettes":[{"color":[250,249,249],"ratio":57},{"color":[182,144,154],"ratio":21},{"color":[81,62,70],"ratio":14},{"color":[156,79,108],"ratio":3.8},{"color":[207,78,127],"ratio":2.76},{"color":[123,124,125],"ratio":0.3}]}