{"id":"MBH2SEJYEXW0Q","name":"200-2004155_magical-girl-lyrical-nanoha-strikers-wallpaper-nightcore-e","size":4992824,"btime":1748988825267,"mtime":1748988827773,"ext":"jpg","tags":[],"folders":[],"isDeleted":false,"url":"","annotation":"","modificationTime":1748988828204,"height":2200,"width":3200,"lastModified":1748988828607,"palettes":[{"color":[29,20,33],"ratio":38},{"color":[236,215,227],"ratio":25},{"color":[140,100,138],"ratio":13},{"color":[94,59,92],"ratio":7},{"color":[162,133,181],"ratio":6},{"color":[107,76,126],"ratio":5},{"color":[204,137,165],"ratio":2.09},{"color":[173,158,189],"ratio":1.25},{"color":[198,123,100],"ratio":0.44}]}