{"id":"M80QSHVIUQIPM","name":"bc4e12e057a068e1903c7742250ea4dd","size":210591,"btime":1741470868811,"mtime":1741470869592,"ext":"jpg","tags":[],"folders":["M80QMPZ1D0V7I"],"isDeleted":false,"url":"","annotation":"","modificationTime":1741470869594,"height":1000,"width":1000,"lastModified":1741470869726,"palettes":[{"color":[237,238,230],"ratio":45},{"color":[145,145,189],"ratio":15},{"color":[108,132,174],"ratio":9},{"color":[151,183,208],"ratio":9},{"color":[92,83,142],"ratio":7},{"color":[119,93,71],"ratio":6},{"color":[219,192,134],"ratio":1.76},{"color":[159,137,125],"ratio":1.61},{"color":[209,161,82],"ratio":0.84},{"color":[221,206,177],"ratio":0.82},{"color":[219,186,85],"ratio":0.69}]}