{"id":"MBH2RAZDYUKOU","name":"fantasy-anime-1920-x-1080-wallpaper-a30khj255sukhbnc","size":247084,"btime":1748988773979,"mtime":1748988773993,"ext":"jpg","tags":[],"folders":[],"isDeleted":false,"url":"","annotation":"","modificationTime":1748988774007,"height":1080,"width":1920,"lastModified":1748988774191,"palettes":[{"color":[118,114,101],"ratio":25},{"color":[33,41,38],"ratio":18},{"color":[200,207,214],"ratio":15},{"color":[235,191,110],"ratio":10},{"color":[158,166,172],"ratio":10},{"color":[172,121,32],"ratio":8},{"color":[186,148,98],"ratio":6},{"color":[93,62,33],"ratio":3.63},{"color":[197,197,183],"ratio":0.96}]}