{"id":"M85MFE1UWF9T2","name":"70omsknn4tb41","size":945877,"btime":1741765869285,"mtime":1741765869546,"ext":"jpg","tags":[],"folders":["M7X2G6G5ENTHX"],"isDeleted":true,"url":"","annotation":"","modificationTime":1741765869972,"height":4096,"width":3132,"palettes":[{"color":[250,243,234],"ratio":67,"$$hashKey":"object:14335"},{"color":[230,145,142],"ratio":12,"$$hashKey":"object:14337"},{"color":[242,196,180],"ratio":7,"$$hashKey":"object:14336"},{"color":[243,165,167],"ratio":6,"$$hashKey":"object:14340"},{"color":[126,75,74],"ratio":2.77,"$$hashKey":"object:14338"},{"color":[232,199,204],"ratio":2.09,"$$hashKey":"object:14339"}],"deletedTime":1741765874501,"lastModified":1741765875683}