{"id":"MAI4LCTZAU2Y4","name":"97dd865e2bf316a52fc90000d91ce287","size":90352,"btime":1746570157098,"mtime":1746875539122,"ext":"webp","tags":[],"folders":[],"isDeleted":true,"url":"","annotation":"","modificationTime":1746875539511,"width":1000,"height":1500,"lastModified":1748970233990,"palettes":[{"color":[236,228,227],"ratio":87},{"color":[110,162,162],"ratio":7},{"color":[112,84,73],"ratio":2.46},{"color":[163,146,140],"ratio":1.27},{"color":[197,180,177],"ratio":0.4},{"color":[215,201,199],"ratio":0.3}],"deletedTime":1748970233818}