{"id":"M83GFS4MKNIK4","name":"a69b51d7c4010b842a0948af7cc714ae","size":179170,"btime":1741634877850,"mtime":1741634878450,"ext":"jpg","tags":[],"folders":["M7WYQX18Z8VR5"],"isDeleted":false,"url":"","annotation":"","modificationTime":1741634878451,"height":1344,"width":896,"lastModified":1741634878611,"palettes":[{"color":[207,192,171],"ratio":45},{"color":[79,80,83],"ratio":17},{"color":[55,51,53],"ratio":16},{"color":[112,110,107],"ratio":11},{"color":[135,139,137],"ratio":4.04},{"color":[134,87,52],"ratio":2.83},{"color":[164,151,135],"ratio":2.27},{"color":[166,140,111],"ratio":0.36}]}