{"id":"M80QTZYD9AC7E","name":"7a49f56f9345272919f7dbf6415fc52f","size":1901758,"btime":1741470938955,"mtime":1741470940104,"ext":"png","tags":["Great sword"],"folders":["M80QMPZ1D0V7I"],"isDeleted":false,"url":"","annotation":"","modificationTime":1741470940108,"height":1000,"width":1000,"lastModified":1741547867280,"palettes":[{"color":[240,243,227],"ratio":48,"$$hashKey":"object:39989"},{"color":[135,203,202],"ratio":21,"$$hashKey":"object:39994"},{"color":[38,77,75],"ratio":8,"$$hashKey":"object:39997"},{"color":[177,226,217],"ratio":8,"$$hashKey":"object:39993"},{"color":[166,139,69],"ratio":4.66,"$$hashKey":"object:39991"},{"color":[206,194,145],"ratio":2.11,"$$hashKey":"object:39990"},{"color":[64,210,209],"ratio":1.88,"$$hashKey":"object:39998"},{"color":[60,155,148],"ratio":1.88,"$$hashKey":"object:39996"},{"color":[134,96,38],"ratio":1.48,"$$hashKey":"object:39992"},{"color":[60,173,187],"ratio":0.57,"$$hashKey":"object:39995"},{"color":[174,164,129],"ratio":0.56}]}